mlx90640/__init__.py
mlx90640/cli.py
mlx90640/mlx90640.py
mlx90640/libs/aarch64/libmlx90640_driver.so
mlx90640/libs/armv7l/libmlx90640_driver.so
mlx90640/libs/windows/mlx90640_driver.dll
mlx90640/libs/x86_64/libmlx90640_driver.so
mlx90640_driver-1.1.2.dist-info/LICENSE
mlx90640_driver-1.1.2.dist-info/METADATA
mlx90640_driver-1.1.2.dist-info/NOTICE
mlx90640_driver-1.1.2.dist-info/WHEEL
mlx90640_driver-1.1.2.dist-info/entry_points.txt
mlx90640_driver-1.1.2.dist-info/top_level.txt
mlx90640_driver-1.1.2.dist-info/RECORD
