Metadata-Version: 2.1
Name: mlx90640-driver
Version: 1.1.2
Summary: MLX90640 Melexis thermal camera (32x24) rapid prototyping python package (on windows 10, linux pc, raspberry pi, jetson nano, beagle bone, ...)
Home-page: https://github.com/melexis-fir/mlx90640-driver-py
Author: Karel Vanroye
Author-email: kva@melexis.com
Maintainer: melexis-fir
License: Apache License, Version 2.0
Project-URL: Documentation, https://melexis-fir.github.io/mlx90640-driver-py/
Project-URL: Source Code, https://github.com/melexis-fir/mlx90640-driver-py
Project-URL: Issue Tracker, https://github.com/melexis-fir/mlx90640-driver-py/issues
Platform: UNKNOWN
Classifier: Development Status :: 5 - Production/Stable
Classifier: Intended Audience :: Developers
Classifier: License :: OSI Approved :: Apache Software License
Classifier: Operating System :: Microsoft :: Windows
Classifier: Operating System :: POSIX
Classifier: Programming Language :: Python :: 3.6
Classifier: Topic :: Utilities
Requires-Python: >=3.6
